dsmf/__init__.py
dsmf-0.0.2.dist-info/METADATA
dsmf-0.0.2.dist-info/WHEEL
dsmf-0.0.2.dist-info/top_level.txt
dsmf-0.0.2.dist-info/RECORD
